click_tester/__init__.py
click_tester/click_runner_test_case.py
click_tester-1.0.0.dist-info/DESCRIPTION.rst
click_tester-1.0.0.dist-info/METADATA
click_tester-1.0.0.dist-info/RECORD
click_tester-1.0.0.dist-info/WHEEL
click_tester-1.0.0.dist-info/metadata.json
click_tester-1.0.0.dist-info/top_level.txt
test/__init__.py
test/test.py
