Metadata-Version: 2.0
Name: click-tester
Version: 1.0.0
Summary: A unittest.TestCase subclass which providesconvenience methods for testing click commands.
Home-page: http://github.com/CarbonLighthouse/click-tester
Author: CarbonLighthouse
Author-email: UNKNOWN
License: MIT
Keywords: click testing unittest TestCase pocoo
Platform: UNKNOWN
Requires-Dist: click (<7,>=6)
